[
  {
    "answer":"Indigo",
    "category":"Cor"
  },
  {
    "answer":"Iogurte",
    "category":"Comida"
  },
  {
    "answer":"Istoe",
    "category":"JLR"
  },
  {
    "answer":"Inutil",
    "category":"Adjetivo"
  },
  {
    "answer":"Irn Bru",
    "category":"Líquido"
  },
  {
    "answer":"I Mother Earth",
    "category":"Banda"
  },
  {
    "answer":"Intestino grosso",
    "category":"PCH"
  },
  {
    "answer":"Iron Maiden",
    "category":"Banda"
  },
  {
    "answer":"Ivete Sangalo",
    "category":"Celebridade"
  },
  {
    "answer":"Impractical Jokers",
    "category":"Programa de TV"
  },
  {
    "answer":"Ingrid Guimaraes",
    "category":"Ator"
  },
  {
    "answer":"Inspetor",
    "category":"Profissão"
  },
  {
    "answer":"iPod",
    "category":"Eletro Eletrônico"
  },
  {
    "answer":"Islands of Nyne",
    "category":"Game"
  },
  {
    "answer":"Ilustrador",
    "category":"Profissão"
  },
  {
    "answer":"Indonesio",
    "category":"Gentílico"
  },
  {
    "answer":"If I Could Fly",
    "category":"Música"
  },
  {
    "answer":"Itapecerica da Serra",
    "category":"Cidade"
  },
  {
    "answer":"Instrutor",
    "category":"Profissão"
  },
  {
    "answer":"Independent",
    "category":"Marca"
  },
  {
    "answer":"Iguana",
    "category":"Animal"
  },
  {
    "answer":"Ipanema",
    "category":"Marca"
  },
  {
    "answer":"Iaque",
    "category":"Animal"
  },
  {
    "answer":"Ingresse",
    "category":"App ou site"
  },
  {
    "answer":"Idiofone",
    "category":"Instrumento Musical"
  },
  {
    "answer":"Inspetor Bugiganga",
    "category":"Filme"
  },
  {
    "answer":"Intestino delgado",
    "category":"PCH"
  },
  {
    "answer":"Irlanda",
    "category":"CEP"
  },
  {
    "answer":"Invasor Zim",
    "category":"Desenho animado"
  },
  {
    "answer":"Impressoes do Brasil",
    "category":"Programa de TV"
  },
  {
    "answer":"Invicta",
    "category":"Marca"
  },
  {
    "answer":"Iris",
    "category":"PCH"
  },
  {
    "answer":"iTranslate",
    "category":"App ou site"
  },
  {
    "answer":"Iris",
    "category":"Flor"
  },
  {
    "answer":"Ibapo",
    "category":"FLV"
  },
  {
    "answer":"Islamabad",
    "category":"Capital"
  },
  {
    "answer":"Itatiaia",
    "category":"Marca"
  },
  {
    "answer":"Iatismo",
    "category":"Esporte"
  },
  {
    "answer":"Ivan Rakitic",
    "category":"Esportista"
  },
  {
    "answer":"I Want You Back",
    "category":"Música"
  },
  {
    "answer":"If You Have Ghosts",
    "category":"Música"
  },
  {
    "answer":"I Wanna Be Adored",
    "category":"Música"
  },
  {
    "answer":"Instrumentista",
    "category":"Profissão"
  },
  {
    "answer":"Iogurte",
    "category":"Sobremesa"
  },
  {
    "answer":"Intercine",
    "category":"Programa de TV"
  },
  {
    "answer":"Infusao",
    "category":"Líquido"
  },
  {
    "answer":"Indila",
    "category":"Cantor"
  },
  {
    "answer":"Iris Allen",
    "category":"PDA"
  },
  {
    "answer":"I Got The Blues",
    "category":"Música"
  },
  {
    "answer":"ica",
    "category":"Inseto"
  },
  {
    "answer":"I Kissed A Girl",
    "category":"Música"
  },
  {
    "answer":"Irresistor",
    "category":"Marca"
  },
  {
    "answer":"Illesteva",
    "category":"Marca"
  },
  {
    "answer":"I Miss You",
    "category":"Música"
  },
  {
    "answer":"Idea",
    "category":"Carro"
  },
  {
    "answer":"Inga",
    "category":"Fruta"
  },
  {
    "answer":"I Wanna Love You",
    "category":"Música"
  },
  {
    "answer":"Intestino",
    "category":"PCH"
  },
  {
    "answer":"Indianapolis",
    "category":"Cidade"
  },
  {
    "answer":"italia",
    "category":"país"
  },
  {
    "answer":"irlanda",
    "category":"país"
  },
  {
    "answer":"igor",
    "category":"nome"
  },
  {
    "answer":"irineu",
    "category":"nome"
  },
  {
    "answer":"irritante",
    "category":"msé"
  },
  {
    "answer":"inhapim",
    "category":"ave"
  },
  {
    "answer":"ingles",
    "category":"idioma"
  },
  {
    "answer":"ingerir",
    "category":"verbo"
  },
  {
    "answer":"imitar",
    "category":"verbo"
  },
  {
    "answer":"isqueiro",
    "category":"objeto"
  },
  {
    "answer":"inalador",
    "category":"objeto"
  },
  {
    "answer":"ima",
    "category":"objeto"
  },
  {
    "answer":"ironman",
    "category":"super-herói"
  },
  {
    "answer":"indio",
    "category":"fantasia"
  },
  {
    "answer":"improve",
    "category":"palavra em inglês"
  },
  {
    "answer":"investigation",
    "category":"palavra em inglês"
  },
  {
    "answer":"insonia",
    "category":"doença"
  },
  {
    "answer":"infertilidade",
    "category":"doença"
  },
  {
    "answer":"iron man",
    "category":"personagem fictício"
  },
  {
    "answer":"indri indri",
    "category":"mamífero"
  },
  {
    "answer":"ioio",
    "category":"brinquedo"
  }
]